backup_and_restore_linux_config/__init__.py
backup_and_restore_linux_config/backup.py
backup_and_restore_linux_config/common.py
backup_and_restore_linux_config/restore.py
backup_and_restore_linux_config/test.py
backup_and_restore_linux_config-0.0.4.dist-info/METADATA
backup_and_restore_linux_config-0.0.4.dist-info/WHEEL
backup_and_restore_linux_config-0.0.4.dist-info/entry_points.txt
backup_and_restore_linux_config-0.0.4.dist-info/top_level.txt
backup_and_restore_linux_config-0.0.4.dist-info/RECORD
