Metadata-Version: 2.1
Name: backup-and-restore-linux-config
Version: 0.0.4
Summary: UNKNOWN
Home-page: UNKNOWN
License: UNKNOWN
Platform: UNKNOWN
Requires-Dist: click
Requires-Dist: colorama ; python_version > "2"
